hexfix/__init__.py
hexfix/checksum.py
hexfix/merge.py
hexfix-0.0.3.dist-info/LICENSE
hexfix-0.0.3.dist-info/METADATA
hexfix-0.0.3.dist-info/WHEEL
hexfix-0.0.3.dist-info/top_level.txt
hexfix-0.0.3.dist-info/RECORD
