Metadata-Version: 2.1
Name: hexfix
Version: 0.0.3
Home-page: https://github.com/ShashikumarKL/hexfix.git
Author: Shashikumar K L
Author-email: raghashashikumar@gmail.com
Classifier: Programming Language :: Python :: 3
Classifier: License :: OSI Approved :: MIT License
Classifier: Operating System :: OS Independent
Requires-Python: >=3.9
License-File: LICENSE
